define.v
    `define NOP 4'h0
    `define OP_ADD 4'h1
    `define OP_SUB 4'h2
    `define OP_AND 4'h3
    `define OP_OR 4'h4
    `define OP_XOR 4'h5
    `define OP_LOADI 4'h6

ALU.v
//ALU.v
`include "define.v"
module ALU (ck, res, L,R, OP, O);
    input ck, res;
    input [15:0] L,R;
    input [3:0] OP;
    output[15:0] O;

    reg [15:0] O;

    always @(posedge ck or posedge res) begin
        if( res )begin
            O <= 16'hzzzz;
        end
        else begin
            case (OP)
                `OP_ADD: O <= L + R;
                `OP_SUB: O <= L - R;
                `OP_AND: O <= L & R;
                `OP_OR: O <= L | R;
                `OP_XOR: O <= L ^ R;   
                `OP_LOADI: O <= R;
                default: O <= 16'hzzzz;
            endcase
        end
    end
endmodule

regfile.v
//Regfile.v Ferdi Rangkuti B233378
 
module regfile (ck, res, O, LSEL, LOUT, RSEL, ROUT, OSEL, OIN, L, R);

input ck, res;
input LOUT, ROUT, OIN;
input [2:0] LSEL,RSEL,OSEL;
input [15:0] O;

output[15:0] L, R;

reg [15:0] r0,r1,r2,r3,r4,r5,r6,r7;
reg [15:0] L, R;

always @(posedge ck or posedge res) begin
    if (res) begin
        r0 <= 16'h0;
        r1 <= 16'h0;
        r2 <= 16'h0;
        r3 <= 16'h0;
        r4 <= 16'h0;
        r5 <= 16'h0;
        r6 <= 16'h0;
        r7 <= 16'h0;
        L <= 16'hzzzz;
        R <= 16'hzzzz;
    end else begin
        if(LOUT) begin
            case(LSEL)
                3'd0: L <= r0;
                3'd1: L <= r1;
                3'd2: L <= r2;
                3'd3: L <= r3;
                3'd4: L <= r4;
                3'd5: L <= r5;
                3'd6: L <= r6;
                3'd7: L <= r7;
            endcase
        end else begin
            L <= 16'hzzzz;
        end

        if(ROUT) begin
            case(RSEL)
                3'd0: R <= r0;
                3'd1: R <= r1;
                3'd2: R <= r2;
                3'd3: R <= r3;
                3'd4: R <= r4;
                3'd5: R <= r5;
                3'd6: R <= r6;
                3'd7: R <= r7;
            endcase
        end else begin
            R <= 16'hzzzz;
        end

        if(OIN) begin
            case(OSEL)
                3'd0: r0 <= O;
                3'd1: r1 <= O;
                3'd2: r2 <= O;
                3'd3: r3 <= O;
                3'd4: r4 <= O;
                3'd5: r5 <= O;
                3'd6: r6 <= O;
                3'd7: r7 <= O;
            endcase
        end
    end
end

endmodule

decoder.v
//decoder.v //Ferdi Rizaldi Rangkuti
`include "define.v"
module decoder(ck, res, INST, OP, LSEL, RSEL, OSEL, LOUT, ROUT, OIN, R);
    input ck, res;
    input[15:0] INST;
    
    output LOUT, ROUT, OIN;
    output[2:0] LSEL, RSEL, OSEL;
    output[15:0] R;
    output[3:0] OP;

    reg LOUT, ROUT, OIN;
    reg[2:0] LSEL, RSEL, OSEL;
    reg[15:0] R;
    reg[3:0] OP;

    always @(posedge ck or posedge res) begin
        if(res) begin
            R <= 16'hzzzz;
            OP <= 0;
            LSEL <= 0;
            LOUT <= 0;
            RSEL <= 0;
            ROUT <= 0;
            OSEL <= 0;
            OIN <= 0;
        end else begin
            if(INST[15:12]==`OP_ADD||INST[15:12]== `OP_SUB||INST[15:12]== `OP_AND||INST[15:12]==`OP_OR||INST[15:12]== `OP_XOR) begin
                OP <= INST[15:12];
                LSEL <= INST[8:6];
                LOUT <= 1;
                RSEL <= INST[5:3];
                ROUT <= 1;
                OSEL <= INST[11:9];
                OIN <= 1;
                R <= 16'hzzzz;
            end else if(INST[15:12]==`OP_LOADI) begin
                OP <= INST[15:12];
                OSEL <= INST[11:9];
                OIN <= 1;
                LOUT <= 0;
                ROUT <= 0;
                R <= {7'h00,INST[8:0]};
            end
        end  
    end

endmodule

CPU1.v
//CPU1.v Ferdi Rizaldi Rangkuti
`include "decoder.v"
`include "ALU.v"
`include "regfile.v"

module CPU1(ck,res, INST);
    input ck, res;
    input[15:0] INST;

    wire[3:0] op;
    wire lout,rout,oin;
    wire[2:0] lsel, rsel, osel;
    wire[15:0] rbus,lbus,obus;
    
    reg[2:0] cpu_state;

    wire dec_oin;
    wire reg_oin;

    parameter CPU_STATE_IF = 3'h0;
    parameter CPU_STATE_ID = 3'h1;
    parameter CPU_STATE_REG = 3'h2;
    parameter CPU_STATE_EX = 3'h3;
    parameter CPU_STATE_WB = 3'h4;
    
    decoder decoder(
        .ck(ck), 
        .res(res), 
        .INST(INST), 
        .OP(op), 
        .LSEL(lsel), 
        .RSEL(rsel), 
        .OSEL(osel), 
        .LOUT(lout), 
        .ROUT(rout), 
        .OIN(dec_oin), 
        .R(rbus)
    );

    regfile register(
        .ck(ck),
        .res(res),
        .O(obus),
        .LSEL(lsel),
        .LOUT(lout),
        .RSEL(rsel),
        .ROUT(rout),
        .OSEL(osel),
        .OIN(reg_oin),
        .L(lbus),
        .R(rbus)
    );

    ALU ALU(
        .ck(ck),
        .res(res),

        .L(lbus),
        .R(rbus),
        .OP(op),
        .O(obus)
    );
    assign reg_oin = (cpu_state == CPU_STATE_WB)?dec_oin:1'b0;
    
    
    always @(posedge ck or posedge res)begin
        if(res) begin
            cpu_state <= 3'h0;
        end else begin 
            if(cpu_state== CPU_STATE_IF)begin
                cpu_state <= CPU_STATE_ID;
            end if(cpu_state== CPU_STATE_ID)begin
                cpu_state <= CPU_STATE_REG;
            end if(cpu_state== CPU_STATE_REG)begin
                cpu_state <= CPU_STATE_EX;
            end if(cpu_state== CPU_STATE_EX)begin
                cpu_state <= CPU_STATE_WB;
            end if(cpu_state== CPU_STATE_WB)begin
                cpu_state <= CPU_STATE_IF;
            end
        end
    end
endmodule

CPU1_tp.v
`timescale 1ps/1ps
`include "define.v"

`define REG_R1 3'h1
`define REG_R2 3'h2
`define REG_R3 3'h3

module CPU1_tp;

reg ck,res;
reg[15:0] INST;

parameter STEP = 1000000;

CPU1 CPU1(ck, res, INST);

always begin
    ck = 0; #(STEP/2);
    ck = 1; #(STEP/2);
end

initial begin
    $dumpfile("CPU1.vcd");
    $dumpvars(0, CPU1_tp);

        res=1;
    // load 5 to the register h1
    #(STEP*5) res =0 ;INST = {`OP_LOADI, `REG_R1, 9'h5};
    // load 3 to the register h1
    #(STEP*5) INST = {`OP_LOADI, `REG_R2, 9'h3};
    // add r1 and r2 and write it back to r3
    #(STEP*5) INST = {`OP_ADD, `REG_R3, `REG_R1, `REG_R2, 3'h0};
    // add r1 and r2 and write it back to r3
    #(STEP*5) INST = {`OP_SUB, `REG_R3, `REG_R3, `REG_R1, 3'h0};
    #(STEP*5) $finish;
end 

initial $monitor ($time, "ck=%b, res=%b,INST=%h",ck,res,INST);


endmodule

CPU1.vcd
$date
	Fri May 26 16:34:14 2023
$end
$version
	Icarus Verilog
$end
$timescale
	1ps
$end
$scope module CPU1_tp $end
$var reg 16 ! INST [15:0] $end
$var reg 1 " ck $end
$var reg 1 # res $end
$scope module CPU1 $end
$var wire 16 $ INST [15:0] $end
$var wire 1 " ck $end
$var wire 16 % rbus [15:0] $end
$var wire 1 # res $end
$var wire 3 & rsel [2:0] $end
$var wire 1 ' rout $end
$var wire 1 ( reg_oin $end
$var wire 3 ) osel [2:0] $end
$var wire 4 * op [3:0] $end
$var wire 16 + obus [15:0] $end
$var wire 3 , lsel [2:0] $end
$var wire 1 - lout $end
$var wire 16 . lbus [15:0] $end
$var wire 1 / dec_oin $end
$var reg 3 0 cpu_state [2:0] $end
$scope module ALU $end
$var wire 16 1 R [15:0] $end
$var wire 1 " ck $end
$var wire 1 # res $end
$var wire 4 2 OP [3:0] $end
$var wire 16 3 L [15:0] $end
$var reg 16 4 O [15:0] $end
$upscope $end
$scope module decoder $end
$var wire 16 5 INST [15:0] $end
$var wire 1 " ck $end
$var wire 1 # res $end
$var reg 1 - LOUT $end
$var reg 3 6 LSEL [2:0] $end
$var reg 1 / OIN $end
$var reg 4 7 OP [3:0] $end
$var reg 3 8 OSEL [2:0] $end
$var reg 16 9 R [15:0] $end
$var reg 1 ' ROUT $end
$var reg 3 : RSEL [2:0] $end
$upscope $end
$scope module register $end
$var wire 1 - LOUT $end
$var wire 3 ; LSEL [2:0] $end
$var wire 16 < O [15:0] $end
$var wire 1 ( OIN $end
$var wire 3 = OSEL [2:0] $end
$var wire 1 ' ROUT $end
$var wire 3 > RSEL [2:0] $end
$var wire 1 " ck $end
$var wire 1 # res $end
$var reg 16 ? L [15:0] $end
$var reg 16 @ R [15:0] $end
$var reg 16 A r0 [15:0] $end
$var reg 16 B r1 [15:0] $end
$var reg 16 C r2 [15:0] $end
$var reg 16 D r3 [15:0] $end
$var reg 16 E r4 [15:0] $end
$var reg 16 F r5 [15:0] $end
$var reg 16 G r6 [15:0] $end
$var reg 16 H r7 [15:0] $end
$upscope $end
$upscope $end
$upscope $end
$enddefinitions $end
#0
$dumpvars
b0 H
b0 G
b0 F
b0 E
b0 D
b0 C
b0 B
b0 A
bz @
bz ?
b0 >
b0 =
bz <
b0 ;
b0 :
bz 9
b0 8
b0 7
b0 6
bx 5
bz 4
bz 3
b0 2
bz 1
b0 0
0/
bz .
0-
b0 ,
bz +
b0 *
b0 )
0(
0'
b0 &
bz %
bx $
1#
0"
bx !
$end
#500000
1"
#1000000
0"
#1500000
1"
#2000000
0"
#2500000
1"
#3000000
0"
#3500000
1"
#4000000
0"
#4500000
1"
#5000000
0"
b110001000000101 !
b110001000000101 $
b110001000000101 5
0#
#5500000
b101 %
b101 1
b101 9
1/
b1 )
b1 8
b1 =
b110 *
b110 2
b110 7
b1 0
1"
#6000000
0"
#6500000
b10 0
b101 +
b101 4
b101 <
1"
#7000000
0"
#7500000
b11 0
1"
#8000000
0"
#8500000
1(
b100 0
1"
#9000000
0"
#9500000
0(
b101 B
b0 0
1"
#10000000
0"
b110010000000011 !
b110010000000011 $
b110010000000011 5
#10500000
b1 0
b11 %
b11 1
b11 9
b10 )
b10 8
b10 =
1"
#11000000
0"
#11500000
b11 +
b11 4
b11 <
b10 0
1"
#12000000
0"
#12500000
b11 0
1"
#13000000
0"
#13500000
1(
b100 0
1"
#14000000
0"
#14500000
0(
b0 0
b11 C
1"
#15000000
0"
b1011001010000 !
b1011001010000 $
b1011001010000 5
#15500000
bz %
bz 1
bz 9
b11 )
b11 8
b11 =
1'
b10 &
b10 :
b10 >
1-
b1 ,
b1 6
b1 ;
b1 *
b1 2
b1 7
b1 0
1"
#16000000
0"
#16500000
b10 0
bx +
bx 4
bx <
b11 %
b11 1
b11 @
b101 .
b101 3
b101 ?
1"
#17000000
0"
#17500000
b1000 +
b1000 4
b1000 <
b11 0
1"
#18000000
0"
#18500000
1(
b100 0
1"
#19000000
0"
#19500000
0(
b1000 D
b0 0
1"
#20000000
0"
b10011011001000 !
b10011011001000 $
b10011011001000 5
#20500000
b1 0
b1 &
b1 :
b1 >
b11 ,
b11 6
b11 ;
b10 *
b10 2
b10 7
1"
#21000000
0"
#21500000
b101 %
b101 1
b101 @
b1000 .
b1000 3
b1000 ?
b10 +
b10 4
b10 <
b10 0
1"
#22000000
0"
#22500000
b11 0
b11 +
b11 4
b11 <
1"
#23000000
0"
#23500000
1(
b100 0
1"
#24000000
0"
#24500000
0(
b0 0
b11 D
1"
